hoi4dev/__init__.py
hoi4dev/cli.py
hoi4dev/achievements/__init__.py
hoi4dev/bops/__init__.py
hoi4dev/characters/__init__.py
hoi4dev/countries/__init__.py
hoi4dev/decisions/__init__.py
hoi4dev/diplomacy/__init__.py
hoi4dev/divisions/__init__.py
hoi4dev/equipments/__init__.py
hoi4dev/events/__init__.py
hoi4dev/focuses/__init__.py
hoi4dev/ideas/__init__.py
hoi4dev/ideologies/__init__.py
hoi4dev/init/__init__.py
hoi4dev/intelligence_agencies/__init__.py
hoi4dev/maps/__init__.py
hoi4dev/maps/map2graph.py
hoi4dev/maps/map2img.py
hoi4dev/maps/state_stats.py
hoi4dev/modifiers/__init__.py
hoi4dev/resources/configs/buildings.json
hoi4dev/resources/configs/config.json
hoi4dev/resources/configs/copy.json
hoi4dev/resources/configs/equipmentdesigner.json
hoi4dev/resources/configs/equipmentdesigner_window.json
hoi4dev/resources/configs/equipmentdesigner_window_special.json
hoi4dev/resources/configs/manpower.json
hoi4dev/resources/configs/paths.json
hoi4dev/resources/configs/portraits.json
hoi4dev/resources/configs/resources.json
hoi4dev/resources/configs/super_event.json
hoi4dev/resources/configs/super_event_gfx.json
hoi4dev/resources/configs/super_event_gui.json
hoi4dev/resources/configs/super_event_localisation_desc.json
hoi4dev/resources/configs/super_event_localisation_mark.json
hoi4dev/resources/configs/super_event_localisation_name.json
hoi4dev/resources/configs/term_table.json
hoi4dev/resources/imgs/Super_Event_Close_Button.dds
hoi4dev/resources/imgs/Super_Event_Underlay.dds
hoi4dev/resources/imgs/Super_Event_Window.dds
hoi4dev/resources/imgs/advisor_template.dds
hoi4dev/resources/imgs/country_event_template.dds
hoi4dev/resources/imgs/defaults/X.dds
hoi4dev/resources/imgs/defaults/default_achievement.dds
hoi4dev/resources/imgs/defaults/default_bop.dds
hoi4dev/resources/imgs/defaults/default_equipment.dds
hoi4dev/resources/imgs/defaults/default_event.dds
hoi4dev/resources/imgs/defaults/default_flag.dds
hoi4dev/resources/imgs/defaults/default_focus.dds
hoi4dev-0.1.0.8.dist-info/LICENSE
hoi4dev-0.1.0.8.dist-info/METADATA
hoi4dev-0.1.0.8.dist-info/WHEEL
hoi4dev-0.1.0.8.dist-info/entry_points.txt
hoi4dev-0.1.0.8.dist-info/top_level.txt
hoi4dev-0.1.0.8.dist-info/RECORD
