Metadata-Version: 2.1
Name: hoi4dev
Version: 0.1.0.8
Summary: HOI4DEV: Hearts of Iron IV Development Tools
Home-page: https://github.com/Magolor/
Author: Magolor
Author-email: magolorcz@gmail.com
Project-URL: Author, https://github.com/Magolor/
Classifier: Development Status :: 3 - Alpha
Classifier: Intended Audience :: Developers
Classifier: Topic :: Software Development :: Build Tools
Classifier: License :: OSI Approved :: MIT License
Classifier: Programming Language :: Python :: 3
Classifier: Operating System :: MacOS :: MacOS X
Classifier: Operating System :: Microsoft :: Windows
Requires-Python: >=3.9, <4
License-File: LICENSE
Requires-Dist: click~=8.1.7
Requires-Dist: jsonlines~=4.0.0
Requires-Dist: numpy<2.0.0,>=1.26.4
Requires-Dist: openai~=1.57.1
Requires-Dist: pandas~=2.0.3
Requires-Dist: pdoc~=15.0.0
Requires-Dist: pillow~=10.3.0
Requires-Dist: pyheaven>=0.1.6.5
Requires-Dist: send2trash~=1.8.0
Requires-Dist: Wand~=0.6.13
